picoscope/__init__.py
picoscope/_version.py
picoscope/darwin_utils.py
picoscope/error_codes.py
picoscope/picobase.py
picoscope/ps2000.py
picoscope/ps2000a.py
picoscope/ps3000.py
picoscope/ps3000a.py
picoscope/ps4000.py
picoscope/ps4000a.py
picoscope/ps5000.py
picoscope/ps5000a.py
picoscope/ps6000.py
picoscope/ps6000a.py
picoscope-0.7.31.dist-info/LICENSE.md
picoscope-0.7.31.dist-info/METADATA
picoscope-0.7.31.dist-info/WHEEL
picoscope-0.7.31.dist-info/top_level.txt
picoscope-0.7.31.dist-info/RECORD
