Metadata-Version: 2.1
Name: picoscope
Version: 0.7.31
Summary: Unofficial python wrapper for the PicoScope devices.
Home-page: https://github.com/colinoflynn/pico-python/
Author: Colin O'Flynn, Mark Harfouche
Author-email: coflynn@newae.com, mark.harfouche@gmail.com
License: BSD
Keywords: picoscope peripherals hardware oscilloscope ATE
Classifier: Development Status :: 4 - Beta
Classifier: Intended Audience :: Developers
Classifier: Topic :: Software Development :: Libraries
Classifier: Topic :: System :: Hardware
Classifier: Topic :: Scientific/Engineering
Classifier: License :: OSI Approved :: BSD License
Classifier: Programming Language :: Python :: 2.7
Classifier: Programming Language :: Python :: 3
License-File: LICENSE.md
Requires-Dist: numpy
